starforge/__init__.py
starforge/cache.py
starforge/cli.py
starforge/io.py
starforge/util.py
starforge/commands/__init__.py
starforge/commands/cmd_bdist_wheel.py
starforge/commands/cmd_sdist.py
starforge/commands/cmd_wheel.py
starforge/commands/cmd_wheel_diff.py
starforge/config/__init__.py
starforge/config/default.yml
starforge/config/wheels.py
starforge/execution/__init__.py
starforge/execution/docker.py
starforge/execution/local.py
starforge/execution/qemu.py
starforge/forge/__init__.py
starforge/forge/wheels.py
starforge/interface/__init__.py
starforge/interface/wheel.py
starforge-0.3.6.dist-info/DESCRIPTION.rst
starforge-0.3.6.dist-info/METADATA
starforge-0.3.6.dist-info/RECORD
starforge-0.3.6.dist-info/WHEEL
starforge-0.3.6.dist-info/entry_points.txt
starforge-0.3.6.dist-info/metadata.json
starforge-0.3.6.dist-info/top_level.txt
