Metadata-Version: 2.0
Name: starforge
Version: 0.3.6
Summary: Build Galaxy things in virtualized environments
Home-page: https://github.com/galaxyproject/starforge
Author: The Galaxy Community
Author-email: galaxy-dev@lists.galaxyproject.org
License: MIT
Keywords: starforge galaxy docker qemu
Platform: UNKNOWN
Classifier: License :: OSI Approved :: MIT License
Classifier: Natural Language :: English
Classifier: Operating System :: POSIX
Classifier: Programming Language :: Python
Classifier: Programming Language :: Python :: 2
Classifier: Programming Language :: Python :: 2.7
Classifier: Programming Language :: Python :: 3
Requires-Dist: pyyaml
Requires-Dist: click
Requires-Dist: requests
Requires-Dist: six
Requires-Dist: wheel
Requires-Dist: ordereddict; python_version=="2.6"
Provides-Extra: lzma
Requires-Dist: backports.lzma; python_version<="3.3" and extra == 'lzma'
Provides-Extra: platform_specific
Requires-Dist: lionshead; extra == 'platform_specific'
